xeopy/__init__.py
xeopy-0.0.0.dist-info/METADATA
xeopy-0.0.0.dist-info/WHEEL
xeopy-0.0.0.dist-info/top_level.txt
xeopy-0.0.0.dist-info/RECORD
