Metadata-Version: 2.1
Name: xeopy
Version: 0.0.0
Summary: No content right now, reserving a name
Author-email: Wojciech Radaczyński <w.radaczynski@gmail.com>
